Metadata-Version: 1.0
Name: girl
Version: 7.7.7
Summary: 蒋付帮utils
Home-page: https://github.com/jiangfubang
Author: Jiang Fubang
Author-email: luckybang@163.com
License: MIT Licence
Keywords: pip,女孩,girl
Platform: any
